Rot13Bruteforce/__init__.py
Rot13Bruteforce/__version__.py
Rot13Bruteforce/main.py
Rot13Bruteforce-1.0.1.dist-info/LICENSE
Rot13Bruteforce-1.0.1.dist-info/METADATA
Rot13Bruteforce-1.0.1.dist-info/WHEEL
Rot13Bruteforce-1.0.1.dist-info/top_level.txt
Rot13Bruteforce-1.0.1.dist-info/RECORD
